VT4002/__init__.py
pyVT4002-0.9.2.dist-info/LICENSE
pyVT4002-0.9.2.dist-info/METADATA
pyVT4002-0.9.2.dist-info/WHEEL
pyVT4002-0.9.2.dist-info/top_level.txt
pyVT4002-0.9.2.dist-info/RECORD
