Metadata-Version: 2.1
Name: pyVT4002
Version: 0.9.2
Summary: A driver for vt4002 Vtsch climate chamber.
Home-page: https://github.com/Embida/pyVT4002
Author: Embida AS
Author-email: post@embida.no
License: UNKNOWN
Platform: UNKNOWN
Classifier: Programming Language :: Python :: 3
Classifier: License :: OSI Approved :: GNU Lesser General Public License v3 (LGPLv3)
Classifier: Operating System :: OS Independent
Requires-Python: >=3.6.0
